seunggabi_core_python/__init__.py
seunggabi_core_python/const.py
seunggabi_core_python/exception/__init__.py
seunggabi_core_python/exception/bad_request.py
seunggabi_core_python/exception/not_found.py
seunggabi_core_python/exception/not_ok.py
seunggabi_core_python/util/__init__.py
seunggabi_core_python/util/arg_util.py
seunggabi_core_python/util/bs_util.py
seunggabi_core_python/util/config_util.py
seunggabi_core_python/util/crypto_util.py
seunggabi_core_python/util/date_util.py
seunggabi_core_python/util/dependency_util.py
seunggabi_core_python/util/env_util.py
seunggabi_core_python/util/file_util.py
seunggabi_core_python/util/json_util.py
seunggabi_core_python/util/math_util.py
seunggabi_core_python/util/mysql_util.py
seunggabi_core_python/util/obj_util.py
seunggabi_core_python/util/redis_util.py
seunggabi_core_python/util/request_util.py
seunggabi_core_python/util/stock_util.py
seunggabi_core_python/util/str_util.py
seunggabi_core_python-1.7.0.dist-info/LICENSE
seunggabi_core_python-1.7.0.dist-info/METADATA
seunggabi_core_python-1.7.0.dist-info/WHEEL
seunggabi_core_python-1.7.0.dist-info/top_level.txt
seunggabi_core_python-1.7.0.dist-info/RECORD
