Metadata-Version: 2.1
Name: seunggabi-core-python
Version: 1.7.0
Summary: A collection of core Python modules
Home-page: https://github.com/seunggabi/core_python
Author: seunggabi
Author-email: seunggabi@gmail.com
Classifier: Development Status :: 3 - Alpha
Classifier: Intended Audience :: Developers
Classifier: License :: OSI Approved :: MIT License
Classifier: Programming Language :: Python :: 3
Classifier: Programming Language :: Python :: 3.6
Classifier: Programming Language :: Python :: 3.7
Classifier: Programming Language :: Python :: 3.8
License-File: LICENSE
Requires-Dist: setuptools
Requires-Dist: wheel
Requires-Dist: twine
Requires-Dist: requests
Requires-Dist: bs4
Requires-Dist: pymysql
Requires-Dist: redis
Requires-Dist: virtualenv
Requires-Dist: black
Requires-Dist: pre-commit
Requires-Dist: pytest
